cdk_cloudformation_stocks_orders_marketorder/__init__.py
cdk_cloudformation_stocks_orders_marketorder/py.typed
cdk_cloudformation_stocks_orders_marketorder/_jsii/__init__.py
cdk_cloudformation_stocks_orders_marketorder/_jsii/stocks-orders-marketorder@1.0.0-alpha.7.jsii.tgz
cdk_cloudformation_stocks_orders_marketorder-1.0.0a7.dist-info/LICENSE
cdk_cloudformation_stocks_orders_marketorder-1.0.0a7.dist-info/METADATA
cdk_cloudformation_stocks_orders_marketorder-1.0.0a7.dist-info/WHEEL
cdk_cloudformation_stocks_orders_marketorder-1.0.0a7.dist-info/top_level.txt
cdk_cloudformation_stocks_orders_marketorder-1.0.0a7.dist-info/RECORD
